[{"id":"d2ccdb7f.8548d8","type":"tab","label":"IRcontroller","disabled":false,"info":""},{"id":"8a0049e7.2957c8","type":"mqtt in","z":"d2ccdb7f.8548d8","name":"","topic":"IR/service","qos":"0","broker":"9dac4739.1fac28","x":840,"y":40,"wires":[["35cd2bd3.63c4d4","afb08449.c11078"]]},{"id":"e5c12ea7.eb6ad","type":"mqtt in","z":"d2ccdb7f.8548d8","name":"","topic":"IR/command","qos":"0","broker":"9dac4739.1fac28","x":850,"y":240,"wires":[["bdae005b.19e9f","a90db2cb.c2652"]]},{"id":"8d44a0d6.843bf","type":"mqtt in","z":"d2ccdb7f.8548d8","name":"","topic":"IR/key","qos":"0","broker":"9dac4739.1fac28","x":830,"y":140,"wires":[["a508a83b.5df638","6308e9b0.144fe8"]]},{"id":"35cd2bd3.63c4d4","type":"json","z":"d2ccdb7f.8548d8","name":"","property":"payload","action":"","pretty":false,"x":1030,"y":40,"wires":[["e91dd7e3.8dca18"]]},{"id":"a508a83b.5df638","type":"json","z":"d2ccdb7f.8548d8","name":"","property":"payload","action":"","pretty":false,"x":1030,"y":140,"wires":[["87ad49a6.b5bba8"]]},{"id":"bdae005b.19e9f","type":"json","z":"d2ccdb7f.8548d8","name":"","property":"payload","action":"","pretty":false,"x":1030,"y":240,"wires":[["357ec8b8.674448"]]},{"id":"e91dd7e3.8dca18","type":"debug","z":"d2ccdb7f.8548d8","name":"","active":true,"tosidebar":true,"console":false,"tostatus":false,"complete":"false","x":1210,"y":40,"wires":[]},{"id":"87ad49a6.b5bba8","type":"debug","z":"d2ccdb7f.8548d8","name":"","active":true,"tosidebar":true,"console":false,"tostatus":false,"complete":"false","x":1210,"y":140,"wires":[]},{"id":"357ec8b8.674448","type":"debug","z":"d2ccdb7f.8548d8","name":"","active":true,"tosidebar":true,"console":false,"tostatus":false,"complete":"false","x":1210,"y":240,"wires":[]},{"id":"5ac1c9d0.c96178","type":"mqtt in","z":"d2ccdb7f.8548d8","name":"","topic":"HT/send","qos":"0","broker":"9dac4739.1fac28","x":840,"y":440,"wires":[["60a3541e.d8220c","4da68e78.b86e5"]]},{"id":"60a3541e.d8220c","type":"json","z":"d2ccdb7f.8548d8","name":"","property":"payload","action":"","pretty":false,"x":1030,"y":440,"wires":[["6c7da0ac.d1c2f","5692e783.88a6c8","900b3ab4.420ed8","2658532a.4b99fc"]]},{"id":"6c7da0ac.d1c2f","type":"debug","z":"d2ccdb7f.8548d8","name":"","active":true,"tosidebar":true,"console":false,"tostatus":false,"complete":"false","x":1210,"y":440,"wires":[]},{"id":"d4cc35b0.50c2a8","type":"mqtt in","z":"d2ccdb7f.8548d8","name":"","topic":"HT/command","qos":"0","broker":"9dac4739.1fac28","x":850,"y":720,"wires":[["fc5d7489.dd1e78","3192134a.0820ec"]]},{"id":"fc5d7489.dd1e78","type":"json","z":"d2ccdb7f.8548d8","name":"","property":"payload","action":"","pretty":false,"x":1030,"y":720,"wires":[["482592c2.21697c"]]},{"id":"482592c2.21697c","type":"debug","z":"d2ccdb7f.8548d8","name":"","active":true,"tosidebar":true,"console":false,"tostatus":false,"complete":"false","x":1210,"y":720,"wires":[]},{"id":"4c776df0.d32bb4","type":"mqtt in","z":"d2ccdb7f.8548d8","name":"","topic":"HT/alert","qos":"0","broker":"9dac4739.1fac28","x":830,"y":340,"wires":[["309f846a.6a533c","d8a80e25.81b8c"]]},{"id":"309f846a.6a533c","type":"json","z":"d2ccdb7f.8548d8","name":"","property":"payload","action":"","pretty":false,"x":1030,"y":340,"wires":[["898637eb.5439d8"]]},{"id":"898637eb.5439d8","type":"debug","z":"d2ccdb7f.8548d8","name":"","active":true,"tosidebar":true,"console":false,"tostatus":false,"complete":"false","x":1210,"y":340,"wires":[]},{"id":"5fb43bcd.fbf584","type":"inject","z":"d2ccdb7f.8548d8","name":"CH -","topic":"","payload":"{\"type\":3,\"value\":16753245,\"length\":32}","payloadType":"str","repeat":"","crontab":"","once":false,"onceDelay":0.1,"x":110,"y":40,"wires":[["adafe2b3.7e369"]]},{"id":"a09adeed.b0d8a","type":"inject","z":"d2ccdb7f.8548d8","name":"CH","topic":"","payload":"{\"type\":3,\"value\":16736925,\"length\":32}","payloadType":"str","repeat":"","crontab":"","once":false,"onceDelay":0.1,"x":270,"y":40,"wires":[["adafe2b3.7e369"]]},{"id":"202ecbbe.e07374","type":"inject","z":"d2ccdb7f.8548d8","name":"CH +","topic":"","payload":"{\"type\":3,\"value\":16769565,\"length\":32}","payloadType":"str","repeat":"","crontab":"","once":false,"onceDelay":0.1,"x":430,"y":40,"wires":[["adafe2b3.7e369"]]},{"id":"e74464cf.f91f28","type":"inject","z":"d2ccdb7f.8548d8","name":"|<<","topic":"","payload":"{\"type\":3,\"value\":16720605,\"length\":32}","payloadType":"str","repeat":"","crontab":"","once":false,"onceDelay":0.1,"x":110,"y":140,"wires":[["adafe2b3.7e369"]]},{"id":"28335fdf.8af2e","type":"inject","z":"d2ccdb7f.8548d8","name":">>|","topic":"","payload":"{\"type\":3,\"value\":16712445,\"length\":32}","payloadType":"str","repeat":"","crontab":"","once":false,"onceDelay":0.1,"x":270,"y":140,"wires":[["adafe2b3.7e369"]]},{"id":"a66fd8b.18db528","type":"inject","z":"d2ccdb7f.8548d8","name":">||","topic":"","payload":"{\"type\":3,\"value\":16761405,\"length\":32}","payloadType":"str","repeat":"","crontab":"","once":false,"onceDelay":0.1,"x":430,"y":140,"wires":[["adafe2b3.7e369"]]},{"id":"da0801f0.e15d1","type":"inject","z":"d2ccdb7f.8548d8","name":"-","topic":"","payload":"{\"type\":3,\"value\":16769055,\"length\":32}","payloadType":"str","repeat":"","crontab":"","once":false,"onceDelay":0.1,"x":110,"y":240,"wires":[["adafe2b3.7e369"]]},{"id":"4b929938.ac87f8","type":"inject","z":"d2ccdb7f.8548d8","name":"+","topic":"","payload":"{\"type\":3,\"value\":16754775,\"length\":32}","payloadType":"str","repeat":"","crontab":"","once":false,"onceDelay":0.1,"x":270,"y":240,"wires":[["adafe2b3.7e369"]]},{"id":"f719bacd.0fbbe8","type":"inject","z":"d2ccdb7f.8548d8","name":"EQ","topic":"","payload":"{\"type\":3,\"value\":16748655,\"length\":32}","payloadType":"str","repeat":"","crontab":"","once":false,"onceDelay":0.1,"x":430,"y":240,"wires":[["adafe2b3.7e369"]]},{"id":"4d648de4.927c34","type":"inject","z":"d2ccdb7f.8548d8","name":"0","topic":"","payload":"{\"type\":3,\"value\":16738455,\"length\":32}","payloadType":"str","repeat":"","crontab":"","once":false,"onceDelay":0.1,"x":110,"y":340,"wires":[["adafe2b3.7e369"]]},{"id":"5930a1c7.4266e","type":"inject","z":"d2ccdb7f.8548d8","name":"100+","topic":"","payload":"{\"type\":3,\"value\":16750695,\"length\":32}","payloadType":"str","repeat":"","crontab":"","once":false,"onceDelay":0.1,"x":270,"y":340,"wires":[["adafe2b3.7e369"]]},{"id":"f5a1cfc3.f631e","type":"inject","z":"d2ccdb7f.8548d8","name":"200+","topic":"","payload":"{\"type\":3,\"value\":16756815,\"length\":32}","payloadType":"str","repeat":"","crontab":"","once":false,"onceDelay":0.1,"x":430,"y":340,"wires":[["adafe2b3.7e369"]]},{"id":"77c37fb7.2ccc","type":"inject","z":"d2ccdb7f.8548d8","name":"1","topic":"","payload":"{\"type\":3,\"value\":16724175,\"length\":32}","payloadType":"str","repeat":"","crontab":"","once":false,"onceDelay":0.1,"x":110,"y":460,"wires":[["adafe2b3.7e369"]]},{"id":"e366e6c2.24c848","type":"inject","z":"d2ccdb7f.8548d8","name":"2","topic":"","payload":"{\"type\":3,\"value\":16718055,\"length\":32}","payloadType":"str","repeat":"","crontab":"","once":false,"onceDelay":0.1,"x":270,"y":460,"wires":[["adafe2b3.7e369"]]},{"id":"8aae183c.8ce828","type":"inject","z":"d2ccdb7f.8548d8","name":"3","topic":"","payload":"{\"type\":3,\"value\":16743045,\"length\":32}","payloadType":"str","repeat":"","crontab":"","once":false,"onceDelay":0.1,"x":430,"y":460,"wires":[["adafe2b3.7e369"]]},{"id":"b0e75bb2.ae3bb8","type":"inject","z":"d2ccdb7f.8548d8","name":"4","topic":"","payload":"{\"type\":3,\"value\":16716015,\"length\":32}","payloadType":"str","repeat":"","crontab":"","once":false,"onceDelay":0.1,"x":110,"y":560,"wires":[["adafe2b3.7e369"]]},{"id":"4dc50eef.cadbc","type":"inject","z":"d2ccdb7f.8548d8","name":"5","topic":"","payload":"{\"type\":3,\"value\":16726215,\"length\":32}","payloadType":"str","repeat":"","crontab":"","once":false,"onceDelay":0.1,"x":270,"y":560,"wires":[["adafe2b3.7e369"]]},{"id":"e983bc29.59ac2","type":"inject","z":"d2ccdb7f.8548d8","name":"6","topic":"","payload":"{\"type\":3,\"value\":16734885,\"length\":32}","payloadType":"str","repeat":"","crontab":"","once":false,"onceDelay":0.1,"x":430,"y":560,"wires":[["adafe2b3.7e369"]]},{"id":"2fc5e717.d649a8","type":"inject","z":"d2ccdb7f.8548d8","name":"7","topic":"","payload":"{\"type\":3,\"value\":16728765,\"length\":32}","payloadType":"str","repeat":"","crontab":"","once":false,"onceDelay":0.1,"x":110,"y":660,"wires":[["adafe2b3.7e369"]]},{"id":"767e9160.fad45","type":"inject","z":"d2ccdb7f.8548d8","name":"8","topic":"","payload":"{\"type\":3,\"value\":16730805,\"length\":32}","payloadType":"str","repeat":"","crontab":"","once":false,"onceDelay":0.1,"x":270,"y":660,"wires":[["adafe2b3.7e369"]]},{"id":"a3e0cbf5.1341b8","type":"inject","z":"d2ccdb7f.8548d8","name":"9","topic":"","payload":"{\"type\":3,\"value\":16732845,\"length\":32}","payloadType":"str","repeat":"","crontab":"","once":false,"onceDelay":0.1,"x":430,"y":660,"wires":[["adafe2b3.7e369"]]},{"id":"2d1ccdf1.d8de32","type":"inject","z":"d2ccdb7f.8548d8","name":"H","topic":"","payload":"{\"HTtype\":\"H\"}","payloadType":"str","repeat":"","crontab":"","once":false,"onceDelay":0.1,"x":110,"y":780,"wires":[["bed3f2e9.4619e"]]},{"id":"93c4683a.dc8e28","type":"inject","z":"d2ccdb7f.8548d8","name":"T","topic":"","payload":"{\"HTtype\":\"T\"}","payloadType":"str","repeat":"","crontab":"","once":false,"onceDelay":0.1,"x":270,"y":780,"wires":[["bed3f2e9.4619e"]]},{"id":"67fe03b2.e5f45c","type":"inject","z":"d2ccdb7f.8548d8","name":"HT","topic":"","payload":"{\"HTtype\":\"HT\"}","payloadType":"str","repeat":"","crontab":"","once":false,"onceDelay":0.1,"x":430,"y":780,"wires":[["bed3f2e9.4619e"]]},{"id":"adafe2b3.7e369","type":"mqtt out","z":"d2ccdb7f.8548d8","name":"","topic":"IR/command","qos":"","retain":"","broker":"9dac4739.1fac28","x":690,"y":240,"wires":[]},{"id":"bed3f2e9.4619e","type":"mqtt out","z":"d2ccdb7f.8548d8","name":"","topic":"HT/command","qos":"","retain":"","broker":"9dac4739.1fac28","x":680,"y":720,"wires":[]},{"id":"40d090a8.18424","type":"mqtt out","z":"d2ccdb7f.8548d8","name":"","topic":"HT/alert","qos":"","retain":"","broker":"9dac4739.1fac28","x":700,"y":340,"wires":[]},{"id":"64e92736.6f8ba8","type":"mqtt out","z":"d2ccdb7f.8548d8","name":"","topic":"HT/send","qos":"","retain":"","broker":"9dac4739.1fac28","x":700,"y":440,"wires":[]},{"id":"f31417ae.685058","type":"function","z":"d2ccdb7f.8548d8","name":"Check HT","func":"    return {payload: \"\\{\\\"HTtype\\\"\\:\\\"HT\\\"\\}\"};","outputs":1,"noerr":0,"x":1360,"y":480,"wires":[["bed3f2e9.4619e"]]},{"id":"5692e783.88a6c8","type":"delay","z":"d2ccdb7f.8548d8","name":"","pauseType":"delay","timeout":"10","timeoutUnits":"minutes","rate":"1","nbRateUnits":"1","rateUnits":"second","randomFirst":"1","randomLast":"5","randomUnits":"seconds","drop":false,"x":1200,"y":480,"wires":[["f31417ae.685058"]]},{"id":"9fabae74.ba6d6","type":"function","z":"d2ccdb7f.8548d8","name":"Turn on the cooler","func":"if(msg.payload.T>35)\n{\nreturn {payload:\"\\{\\\"type\\\"\\:3\\,\\\"value\\\"\\:16750695\\,\\\"length\\\"\\:32\\}\"};\n}","outputs":1,"noerr":0,"x":1530,"y":520,"wires":[["adafe2b3.7e369"]]},{"id":"1d2c1ba9.0d41a4","type":"function","z":"d2ccdb7f.8548d8","name":"alert","func":"if(msg.payload.T>50)\n{\nreturn {payload:\"\\{\\\"\\!\\\"\\:\\\"Too Hot\\\"\\}\"};\n}","outputs":1,"noerr":0,"x":1490,"y":560,"wires":[["40d090a8.18424"]]},{"id":"59be6bb7.197fe4","type":"ui_button","z":"d2ccdb7f.8548d8","name":"","group":"f91abce1.d0357","order":1,"width":"2","height":"1","passthru":false,"label":"CH -","tooltip":"","color":"#FFFFFF","bgcolor":"#F44336","icon":"","payload":"{\"type\":3,\"value\":16753245,\"length\":32}","payloadType":"str","topic":"","x":110,"y":80,"wires":[["adafe2b3.7e369"]]},{"id":"193726bc.31b2c9","type":"ui_button","z":"d2ccdb7f.8548d8","name":"","group":"f91abce1.d0357","order":3,"width":"2","height":"1","passthru":false,"label":"CH +","tooltip":"","color":"#FFFFFF","bgcolor":"#F44336","icon":"","payload":"{\"type\":3,\"value\":16769565,\"length\":32}","payloadType":"str","topic":"","x":430,"y":80,"wires":[["adafe2b3.7e369"]]},{"id":"9ef831bd.43c1b","type":"ui_button","z":"d2ccdb7f.8548d8","name":"","group":"f91abce1.d0357","order":2,"width":"2","height":"1","passthru":false,"label":"CH","tooltip":"","color":"#FFFFFF","bgcolor":"#F44336","icon":"","payload":"{\"type\":3,\"value\":16736925,\"length\":32}","payloadType":"str","topic":"","x":270,"y":80,"wires":[["adafe2b3.7e369"]]},{"id":"ce20b17.4ddd95","type":"ui_button","z":"d2ccdb7f.8548d8","name":"","group":"f91abce1.d0357","order":4,"width":"2","height":"1","passthru":false,"label":"|<<","tooltip":"","color":"#FFFFFF","bgcolor":"#009688","icon":"","payload":"{\"type\":3,\"value\":16720605,\"length\":32}","payloadType":"str","topic":"","x":110,"y":180,"wires":[["adafe2b3.7e369"]]},{"id":"f76ad8ca.e9ebf8","type":"ui_button","z":"d2ccdb7f.8548d8","name":"","group":"f91abce1.d0357","order":6,"width":"2","height":"1","passthru":false,"label":">||","tooltip":"","color":"#FFFFFF","bgcolor":"#4CAF50","icon":"","payload":"{\"type\":3,\"value\":16761405,\"length\":32}","payloadType":"str","topic":"","x":430,"y":180,"wires":[["adafe2b3.7e369"]]},{"id":"9cab48ce.ab2288","type":"ui_button","z":"d2ccdb7f.8548d8","name":"","group":"f91abce1.d0357","order":5,"width":"2","height":"1","passthru":false,"label":">>|","tooltip":"","color":"#FFFFFF","bgcolor":"#009688","icon":"","payload":"{\"type\":3,\"value\":16712445,\"length\":32}","payloadType":"str","topic":"","x":270,"y":180,"wires":[["adafe2b3.7e369"]]},{"id":"afcb7188.65dd2","type":"ui_button","z":"d2ccdb7f.8548d8","name":"","group":"f91abce1.d0357","order":7,"width":"2","height":"1","passthru":false,"label":"-","tooltip":"","color":"#FFFFFF","bgcolor":"#3F51B5","icon":"","payload":"{\"type\":3,\"value\":16769055,\"length\":32}","payloadType":"str","topic":"","x":110,"y":280,"wires":[["adafe2b3.7e369"]]},{"id":"a33e8b21.1a1968","type":"ui_button","z":"d2ccdb7f.8548d8","name":"","group":"f91abce1.d0357","order":9,"width":"2","height":"1","passthru":false,"label":"EQ","tooltip":"","color":"#FFFFFF","bgcolor":"#673AB7","icon":"","payload":"{\"type\":3,\"value\":16748655,\"length\":32}","payloadType":"str","topic":"","x":430,"y":280,"wires":[["adafe2b3.7e369"]]},{"id":"4bb5ec8f.346af4","type":"ui_button","z":"d2ccdb7f.8548d8","name":"","group":"f91abce1.d0357","order":8,"width":"2","height":"1","passthru":false,"label":"+","tooltip":"","color":"#FFFFFF","bgcolor":"#3F51B5","icon":"","payload":"{\"type\":3,\"value\":16754775,\"length\":32}","payloadType":"str","topic":"","x":270,"y":280,"wires":[["adafe2b3.7e369"]]},{"id":"337babb8.adf4e4","type":"ui_button","z":"d2ccdb7f.8548d8","name":"","group":"f91abce1.d0357","order":10,"width":"2","height":"1","passthru":false,"label":"0","tooltip":"","color":"#FFFFFF","bgcolor":"#000000","icon":"","payload":"{\"type\":3,\"value\":16738455,\"length\":32}","payloadType":"str","topic":"","x":110,"y":380,"wires":[["adafe2b3.7e369"]]},{"id":"27e3f2bf.332fde","type":"ui_button","z":"d2ccdb7f.8548d8","name":"","group":"f91abce1.d0357","order":12,"width":"2","height":"1","passthru":false,"label":"200+","tooltip":"","color":"#FFFFFF","bgcolor":"#000000","icon":"","payload":"{\"type\":3,\"value\":16756815,\"length\":32}","payloadType":"str","topic":"","x":430,"y":380,"wires":[["adafe2b3.7e369"]]},{"id":"c51f8fa3.4a9a4","type":"ui_button","z":"d2ccdb7f.8548d8","name":"","group":"f91abce1.d0357","order":11,"width":"2","height":"1","passthru":false,"label":"100+","tooltip":"","color":"#FFFFFF","bgcolor":"#000000","icon":"","payload":"{\"type\":3,\"value\":16750695,\"length\":32}","payloadType":"str","topic":"","x":270,"y":380,"wires":[["adafe2b3.7e369"]]},{"id":"f2b4bc20.9eac2","type":"ui_button","z":"d2ccdb7f.8548d8","name":"","group":"f91abce1.d0357","order":14,"width":"2","height":"1","passthru":false,"label":"1","tooltip":"","color":"#FFFFFF","bgcolor":"#000000","icon":"","payload":"{\"type\":3,\"value\":16724175,\"length\":32}","payloadType":"str","topic":"","x":110,"y":500,"wires":[["adafe2b3.7e369"]]},{"id":"daf9c9da.cac998","type":"ui_button","z":"d2ccdb7f.8548d8","name":"","group":"f91abce1.d0357","order":16,"width":"2","height":"1","passthru":false,"label":"3","tooltip":"","color":"#FFFFFF","bgcolor":"#000000","icon":"","payload":"{\"type\":3,\"value\":16743045,\"length\":32}","payloadType":"str","topic":"","x":430,"y":500,"wires":[["adafe2b3.7e369"]]},{"id":"e6fdb39d.7aa73","type":"ui_button","z":"d2ccdb7f.8548d8","name":"","group":"f91abce1.d0357","order":15,"width":"2","height":"1","passthru":false,"label":"2","tooltip":"","color":"#FFFFFF","bgcolor":"#000000","icon":"","payload":"{\"type\":3,\"value\":16718055,\"length\":32}","payloadType":"str","topic":"","x":270,"y":500,"wires":[["adafe2b3.7e369"]]},{"id":"517cbedb.a0388","type":"ui_button","z":"d2ccdb7f.8548d8","name":"","group":"f91abce1.d0357","order":17,"width":"2","height":"1","passthru":false,"label":"4","tooltip":"","color":"#FFFFFF","bgcolor":"#000000","icon":"","payload":"{\"type\":3,\"value\":16716015,\"length\":32}","payloadType":"str","topic":"","x":110,"y":600,"wires":[["adafe2b3.7e369"]]},{"id":"e289f342.7612a","type":"ui_button","z":"d2ccdb7f.8548d8","name":"","group":"f91abce1.d0357","order":19,"width":"2","height":"1","passthru":false,"label":"6","tooltip":"","color":"#FFFFFF","bgcolor":"#000000","icon":"","payload":"{\"type\":3,\"value\":16734885,\"length\":32}","payloadType":"str","topic":"","x":430,"y":600,"wires":[["adafe2b3.7e369"]]},{"id":"f160eedc.3917d","type":"ui_button","z":"d2ccdb7f.8548d8","name":"","group":"f91abce1.d0357","order":18,"width":"2","height":"1","passthru":false,"label":"5","tooltip":"","color":"#FFFFFF","bgcolor":"#000000","icon":"","payload":"{\"type\":3,\"value\":16726215,\"length\":32}","payloadType":"str","topic":"","x":270,"y":600,"wires":[["adafe2b3.7e369"]]},{"id":"16812e0b.b9f382","type":"ui_button","z":"d2ccdb7f.8548d8","name":"","group":"f91abce1.d0357","order":20,"width":"2","height":"1","passthru":false,"label":"7","tooltip":"","color":"#FFFFFF","bgcolor":"#000000","icon":"","payload":"{\"type\":3,\"value\":16728765,\"length\":32}","payloadType":"str","topic":"","x":110,"y":700,"wires":[["adafe2b3.7e369"]]},{"id":"f9a8983c.98ad98","type":"ui_button","z":"d2ccdb7f.8548d8","name":"","group":"f91abce1.d0357","order":22,"width":"2","height":"1","passthru":false,"label":"9","tooltip":"","color":"#FFFFFF","bgcolor":"#000000","icon":"","payload":"{\"type\":3,\"value\":16732845,\"length\":32}","payloadType":"str","topic":"","x":430,"y":700,"wires":[["adafe2b3.7e369"]]},{"id":"9a2d64ea.6f1d78","type":"ui_button","z":"d2ccdb7f.8548d8","name":"","group":"f91abce1.d0357","order":21,"width":"2","height":"1","passthru":false,"label":"8","tooltip":"","color":"#FFFFFF","bgcolor":"#000000","icon":"","payload":"{\"type\":3,\"value\":16730805,\"length\":32}","payloadType":"str","topic":"","x":270,"y":700,"wires":[["adafe2b3.7e369"]]},{"id":"de6da37b.f26ef","type":"ui_button","z":"d2ccdb7f.8548d8","name":"","group":"f91abce1.d0357","order":24,"width":"2","height":"1","passthru":false,"label":"H","tooltip":"","color":"#FFFFFF","bgcolor":"#607D8B","icon":"","payload":"{\"HTtype\":\"H\"}","payloadType":"str","topic":"","x":110,"y":820,"wires":[["bed3f2e9.4619e"]]},{"id":"e911bb5a.b9abf8","type":"ui_button","z":"d2ccdb7f.8548d8","name":"","group":"f91abce1.d0357","order":26,"width":"2","height":"1","passthru":false,"label":"HT","tooltip":"","color":"#FFFFFF","bgcolor":"#607D8B","icon":"","payload":"{\"HTtype\":\"HT\"}","payloadType":"str","topic":"","x":430,"y":820,"wires":[["bed3f2e9.4619e"]]},{"id":"bc6c2d16.63f13","type":"ui_button","z":"d2ccdb7f.8548d8","name":"","group":"f91abce1.d0357","order":25,"width":"2","height":"1","passthru":false,"label":"T","tooltip":"","color":"#FFFFFF","bgcolor":"#607D8B","icon":"","payload":"{\"HTtype\":\"T\"}","payloadType":"str","topic":"","x":270,"y":820,"wires":[["bed3f2e9.4619e"]]},{"id":"758e7e42.71f6b","type":"ui_chart","z":"d2ccdb7f.8548d8","name":"","group":"41964042.31c0a","order":25,"width":0,"height":0,"label":"","chartType":"line","legend":"false","xformat":"HH:mm:ss","interpolate":"linear","nodata":"","dot":false,"ymin":"","ymax":"","removeOlder":1,"removeOlderPoints":"","removeOlderUnit":"3600","cutout":0,"useOneColor":false,"colors":["#1f77b4","#f06296","#ff7f0e","#2ca02c","#98df8a","#d62728","#808080","#9467bd","#c5b0d5"],"useOldStyle":false,"outputs":2,"x":1570,"y":640,"wires":[[],[]]},{"id":"900b3ab4.420ed8","type":"function","z":"d2ccdb7f.8548d8","name":"creat chart","func":"var value1 = msg.payload.H;\nvar value2 = msg.payload.T;\n \nvar topic1 = \"H\";\nvar topic2 = \"T\";\n \nvar newmsg = [{topic:topic1,payload:value1},\n{topic:topic2, payload:value2}];\n \nreturn newmsg;","outputs":2,"noerr":0,"x":1390,"y":640,"wires":[["758e7e42.71f6b","1b039bfd.f25834"],["758e7e42.71f6b","1b039bfd.f25834"]]},{"id":"1b039bfd.f25834","type":"debug","z":"d2ccdb7f.8548d8","name":"","active":false,"tosidebar":true,"console":false,"tostatus":false,"complete":"false","x":1590,"y":680,"wires":[]},{"id":"afb08449.c11078","type":"ui_text","z":"d2ccdb7f.8548d8","group":"4570733a.61013c","order":25,"width":"0","height":"0","name":"","label":"IR/service","format":"{{msg.payload}}","layout":"col-center","x":1040,"y":80,"wires":[]},{"id":"6308e9b0.144fe8","type":"ui_text","z":"d2ccdb7f.8548d8","group":"4570733a.61013c","order":25,"width":"0","height":"0","name":"","label":"IR/key","format":"{{msg.payload}}","layout":"col-center","x":1030,"y":180,"wires":[]},{"id":"a90db2cb.c2652","type":"ui_text","z":"d2ccdb7f.8548d8","group":"4570733a.61013c","order":25,"width":"0","height":"0","name":"","label":"IR/command","format":"{{msg.payload}}","layout":"col-center","x":1050,"y":280,"wires":[]},{"id":"d8a80e25.81b8c","type":"ui_text","z":"d2ccdb7f.8548d8","group":"4570733a.61013c","order":25,"width":"0","height":"0","name":"","label":"HT/alert","format":"{{msg.payload}}","layout":"col-center","x":1040,"y":380,"wires":[]},{"id":"4da68e78.b86e5","type":"ui_text","z":"d2ccdb7f.8548d8","group":"4570733a.61013c","order":25,"width":"0","height":"0","name":"","label":"HT/send","format":"{{msg.payload}}","layout":"col-center","x":1040,"y":480,"wires":[]},{"id":"3192134a.0820ec","type":"ui_text","z":"d2ccdb7f.8548d8","group":"4570733a.61013c","order":25,"width":"0","height":"0","name":"","label":"HT/command","format":"{{msg.payload}}","layout":"col-center","x":1060,"y":760,"wires":[]},{"id":"6f9ccb9c.754884","type":"rising-edge","z":"d2ccdb7f.8548d8","name":"T>35","threshold":"35","x":1370,"y":520,"wires":[["9fabae74.ba6d6"]]},{"id":"2658532a.4b99fc","type":"function","z":"d2ccdb7f.8548d8","name":"Get T number","func":"return {payload : msg.payload.T};","outputs":1,"noerr":0,"x":1220,"y":520,"wires":[["6f9ccb9c.754884","59233805.8641b8","af807563.c89b98"]]},{"id":"59233805.8641b8","type":"rising-edge","z":"d2ccdb7f.8548d8","name":"T>50","threshold":"50","x":1370,"y":560,"wires":[["1d2c1ba9.0d41a4"]]},{"id":"af807563.c89b98","type":"falling-edge","z":"d2ccdb7f.8548d8","name":"T<20","threshold":"20","x":1370,"y":600,"wires":[["acba06ae.da1f88"]]},{"id":"acba06ae.da1f88","type":"function","z":"d2ccdb7f.8548d8","name":"Turn off the cooler","func":"if(msg.payload.T>35)\n{\nreturn {payload:\"\\{\\\"type\\\"\\:3\\,\\\"value\\\"\\:16732845\\,\\\"length\\\"\\:32\\}\"};\n}","outputs":1,"noerr":0,"x":1530,"y":600,"wires":[["adafe2b3.7e369"]]},{"id":"9dac4739.1fac28","type":"mqtt-broker","z":"","name":"","broker":"localhost","port":"1883","clientid":"","usetls":false,"compatmode":true,"keepalive":"60","cleansession":true,"birthTopic":"","birthQos":"0","birthPayload":"","closeTopic":"","closePayload":"","willTopic":"","willQos":"0","willPayload":""},{"id":"f91abce1.d0357","type":"ui_group","z":"","name":"Key","tab":"d1b9ac28.d3322","order":1,"disp":true,"width":"6","collapse":false},{"id":"41964042.31c0a","type":"ui_group","z":"","name":"HT","tab":"d1b9ac28.d3322","order":2,"disp":true,"width":"6","collapse":false},{"id":"4570733a.61013c","type":"ui_group","z":"","name":"Log","tab":"d1b9ac28.d3322","order":3,"disp":true,"width":"6","collapse":false},{"id":"d1b9ac28.d3322","type":"ui_tab","z":"","name":"IRcontroller","icon":"dashboard","order":2,"disabled":false,"hidden":false}]